full_adder/full_adder.v
//*********************************
// Full adder
// by Ryan Thompson
//*********************************

module full_adder( s, cout, a, b, cin );

output s;       // Result
output cout;    // Carry out
input  a;       // Number to add
input  b;       // Second number to add
input  cin;     // Carry in

wire   w1;
wire   w2;
wire   w3; 

assign w1 = a ^ b;
assign w2 = w1 & cin;
assign w3 = a & b;
assign s = w1 ^ cin;
assign cout = w2 | w3;

endmodule

full_adder/full_adder_tb.v
// **********************************
// Full Adder testbench
// by: Ryan Thompson
// **********************************

module full_adder_tb();
wire sum;
wire cout;
reg  a;
reg  b;
reg  cin;

full_adder FA1( s, cout, a, b, cin );

initial begin
    a = 1'b0; b = 1'b0; cin = 1'b0;
#10 a = 1'b0; b = 1'b0; cin = 1'b1;
#10 a = 1'b0; b = 1'b1; cin = 1'b0;
#10 a = 1'b0; b = 1'b1; cin = 1'b1;
#10 a = 1'b1; b = 1'b0; cin = 1'b0;
#10 a = 1'b1; b = 1'b0; cin = 1'b1;
#10 a = 1'b1; b = 1'b1; cin = 1'b0;
#10 a = 1'b1; b = 1'b1; cin = 1'b1;
#10 $finish;
end

initial $monitor("%b + %b + %b = %b%b", a, b, cin, cout, s);

initial begin
    $dumpfile("full_adder.vcd");
    $dumpvars(0, FA1);
end

endmodule

full_adder/full_adder.vcd
$date
	Sun Jul 12 14:43:14 2020
$end
$version
	Icarus Verilog
$end
$timescale
	1s
$end
$scope module full_adder_tb $end
$scope module FA1 $end
$var wire 1 ! a $end
$var wire 1 " b $end
$var wire 1 # cin $end
$var wire 1 $ cout $end
$var wire 1 % s $end
$var wire 1 & w1 $end
$var wire 1 ' w2 $end
$var wire 1 ( w3 $end
$upscope $end
$upscope $end
$enddefinitions $end
#0
$dumpvars
0(
0'
0&
0%
0$
0#
0"
0!
$end
#10
1%
1#
#20
1&
0#
1"
#30
1$
1'
0%
1#
#40
0$
0'
1%
0#
0"
1!
#50
1$
1'
0%
1#
#60
0'
0&
1(
0#
1"
#70
1%
1#
